{
  "Red Alliance Teams":{
    "1":{
      "339":0,
      "404":0,
      "449":0,
      "623":0,
      "888":0,
      "1111":0,
      "1727":0,
      "1811":0,
      "1885":0,
      "2106":0,
      "2199":0,
      "2377":0,
      "2421":0,
      "2537":0,
      "3714":0,
      "3748":0,
      "3793":0,
      "4464":0,
      "4541":0,
      "5587":0,
      "7770":0,
      "7886":1,
      "8622":0,
      "9403":0,
      "9684":0,
      "9709":0,
      "10224":0,
      "10449":0,
      "10679":0
    }
  },
  "Blue Alliance Teams":{
    "1":{
      "339":0,
      "404":0,
      "449":0,
      "623":0,
      "888":0,
      "1111":0,
      "1727":0,
      "1811":0,
      "1885":0,
      "2106":0,
      "2199":0,
      "2377":0,
      "2421":0,
      "2537":0,
      "3714":0,
      "3748":0,
      "3793":0,
      "4464":0,
      "4541":0,
      "5587":0,
      "7770":0,
      "7886":1,
      "8622":0,
      "9403":0,
      "9684":0,
      "9709":0,
      "10224":0,
      "10449":0,
      "10679":0
    }
  },
  "Red Alliance Score":{
    "1":0
  },
  "Blue Alliance Score":{
    "1":11
  }
}